pyintercon/__init__.py
pyintercon/threads.py
pyintercon-2.1.2.dist-info/LICENSE
pyintercon-2.1.2.dist-info/METADATA
pyintercon-2.1.2.dist-info/WHEEL
pyintercon-2.1.2.dist-info/top_level.txt
pyintercon-2.1.2.dist-info/RECORD
