Metadata-Version: 2.1
Name: pyintercon
Version: 2.1.2
Summary: A module to connect your server and your clients and exchange information with  them
Home-page: https://github.com/Ridoineel/Pyintercon
Author: RidoineEl
Author-email: ridoineelofficiel@gmail.com
License: UNKNOWN
Project-URL: Bug Tracker, https://github.com/Ridoineel/Pyintercon/issues
Platform: UNKNOWN
Classifier: Programming Language :: Python :: 3
Classifier: License :: OSI Approved :: MIT License
Classifier: Operating System :: OS Independent
Requires-Python: >=3.6
License-File: LICENSE
